{"name": "Lion", "hero_type": "intelligence", "base_strength": "18", "str_per_lvl": "2.2", "base_agility": "18", "agi_per_lvl": "1.5", "base_intelligence": "18", "int_per_lvl": "3.5", "base_armor": "-1", "magic_resistance": "25", "status_resistance": "0", "base_min_att_damage": "29", "base_max_att_damage": "35", "bat": "1.7", "base_att_speed": "115", "assertions": {"attacks_per_second_0": "0.68", "attacks_per_second_1": "0.78", "attacks_per_second_15": "0.91", "attacks_per_second_25": "1.06", "attacks_per_second_30": "1.12", "health_0": "200", "health_1": "560", "health_15": "1160", "health_25": "1840", "health_30": "2100", "mana_0": "75", "mana_1": "291", "mana_15": "879", "mana_25": "1443", "mana_30": "1671", "armor_0": "-1", "armor_1": "2", "armor_15": "5.5", "armor_25": "10", "armor_30": "11.58"}}