{"name": "Ogre Magi", "hero_type": "intelligence", "base_strength": "23", "str_per_lvl": "3.3", "base_agility": "14", "agi_per_lvl": "1.5", "base_intelligence": "15", "int_per_lvl": "2.5", "base_armor": "5", "magic_resistance": "25", "status_resistance": "0", "base_min_att_damage": "34", "base_max_att_damage": "40", "bat": "1.7", "base_att_speed": "100", "assertions": {"attacks_per_second_0": "0.59", "attacks_per_second_1": "0.67", "attacks_per_second_15": "0.79", "attacks_per_second_25": "0.95", "attacks_per_second_30": "1.01", "health_0": "200", "health_1": "660", "health_15": "1580", "health_25": "2480", "health_30": "2840", "mana_0": "75", "mana_1": "255", "mana_15": "675", "mana_25": "1119", "mana_30": "1287", "armor_0": "5", "armor_1": "7.33", "armor_15": "10.83", "armor_25": "15.33", "armor_30": "16.92"}}